[{"location":"home","type":"story","start":"2017-05-02T06:47:50","path":"/Users/msc/Writing/king cage","startCount":105588,"project":"king cage","count":1952,"countBy":"average","dictation":false,"end":"2017-05-02T07:59:06","commit":"43323ff02adb5eb1aa95fa22a48abd63254dedc1"},{"location":"home","start":"2017-05-02T08:08:00","type":"story","path":"/Users/msc/Writing/king cage","startCount":105815,"project":"king cage","count":1421,"countBy":"average","dictation":false,"end":"2017-05-02T08:36:54"},{"location":"home","type":"story","start":"2017-05-02T08:57:27","path":"/Users/msc/Writing/king cage","startCount":105815,"project":"king cage","count":1103,"countBy":"average","dictation":false,"end":"2017-05-02T09:41:35","commit":"105987f9dfda4b1cfee887ca610ca34ceba7885a"},{"location":"home","type":"story","start":"2017-05-02T10:13:08","path":"/Users/msc/Writing/king cage","startCount":105846,"project":"king cage","count":1036,"countBy":"average","dictation":false,"end":"2017-05-02T10:36:24","commit":"888040de60f0cf7e7737db7306b7ebd005a4b02e"},{"location":"home","type":"story","start":"2017-05-02T10:54:17","path":"/Users/msc/Writing/king cage","startCount":105816,"project":"king cage","count":1904,"countBy":"average","dictation":false,"end":"2017-05-02T11:29:56","commit":"f3337180dcc4e5bb62a3ca28f385b7fccfb948a5"},{"location":"home","type":"story","start":"2017-05-03T07:00:29","path":"/Users/msc/Writing/king cage","startCount":107815,"project":"king cage","count":1354,"countBy":"average","dictation":false,"end":"2017-05-03T07:32:53","commit":"0123c9c5efa24735a0816fc9d5ca22c5b3ee6168"},{"location":"home","type":"story","start":"2017-05-03T07:47:56","path":"/Users/msc/Writing/king cage","startCount":107838,"project":"king cage","count":1174,"countBy":"average","dictation":false,"end":"2017-05-03T08:23:29","commit":"5b16ff31e1a2adb821ac73f0032487ee39288413"},{"location":"home","type":"story","start":"2017-05-03T08:37:48","path":"/Users/msc/Writing/king cage","startCount":107864,"project":"king cage","count":456,"countBy":"average","dictation":false,"end":"2017-05-03T08:55:29","commit":"d563ea88021d94ddbdaaa83b4bb3381fd0a0a152"},{"location":"train","type":"story","start":"2017-05-03T11:12:55","path":"/Users/msc/Writing/king cage","startCount":107978,"project":"king cage","count":510,"countBy":"average","dictation":false,"end":"2017-05-03T11:36:30","commit":"69301e6e7f663ba583a91167d96ba76c5c64760b"},{"location":"cafe","type":"story","start":"2017-05-03T12:34:33","path":"/Users/msc/Writing/king cage","startCount":108049,"project":"king cage","count":674,"countBy":"average","dictation":false,"end":"2017-05-03T13:07:56","commit":"c0ec875b54c748f430c9822acae99d4107a8d170"},{"location":"cafe","type":"story","start":"2017-05-03T13:21:02","path":"/Users/msc/Writing/king cage","startCount":108164,"project":"king cage","count":1201,"countBy":"average","dictation":false,"end":"2017-05-03T14:25:05","commit":"5d96bb6cb6735923dad087565ff026c692d126cb"},{"location":"home","type":"story","start":"2017-05-04T06:58:13","path":"/Users/msc/Writing/king cage","startCount":127392,"project":"king cage","count":1790,"countBy":"average","dictation":false,"end":"2017-05-04T07:42:51","commit":"a3492957b6908bcb835671b23c66f197c0d0cf94"},{"location":"home","type":"story","start":"2017-05-04T08:08:29","path":"/Users/msc/Writing/king cage","startCount":127451,"project":"king cage","count":1566,"countBy":"average","dictation":false,"end":"2017-05-04T09:03:34","commit":"408244df9cd20a57c79c0afa998ad290d4069810"},{"location":"home","type":"story","start":"2017-05-04T09:16:28","path":"/Users/msc/Writing/king cage","startCount":127465,"project":"king cage","count":1318,"countBy":"average","dictation":false,"end":"2017-05-04T09:53:06","commit":"a00e34157335b0d130ad5731048818b58d0734fa"},{"location":"home","type":"story","start":"2017-05-04T10:10:08","path":"/Users/msc/Writing/king cage","startCount":127382,"project":"king cage","count":109,"countBy":"average","dictation":false,"end":"2017-05-04T10:15:31","commit":"fc45a829d73aed0c66251b2002b6615be1c0106d"},{"location":"home","type":"story","start":"2017-05-04T10:17:21","path":"/Users/msc/Writing/king cage","startCount":127384,"project":"king cage","count":2659,"countBy":"average","dictation":false,"end":"2017-05-04T11:17:35","commit":"8756c7b5190124340748505dc9f12ad416e7e00b"},{"location":"home","type":"story","start":"2017-05-04T14:06:23","path":"/Users/msc/Writing/king cage","startCount":127360,"project":"king cage","count":1722,"countBy":"average","dictation":false,"end":"2017-05-04T14:46:55","commit":"c91923377ece1997e8c7889839b6380a5185a330"},{"location":"home","type":"story","start":"2017-05-05T06:49:07","path":"/Users/msc/Writing/king cage","startCount":125886,"project":"king cage","count":418,"countBy":"average","dictation":false,"end":"2017-05-05T07:03:56","commit":"5f1c459f160ce370fb045adb91847427e7f914e0"},{"location":"home","type":"story","start":"2017-05-05T07:06:01","path":"/Users/msc/Writing/king cage","startCount":125960,"project":"king cage","count":2064,"countBy":"average","dictation":false,"end":"2017-05-05T08:24:26","commit":"2c8785f594ad3b3fcefa1e9bb09933c658523ee4"},{"location":"home","type":"story","start":"2017-05-05T08:43:14","path":"/Users/msc/Writing/king cage","startCount":126082,"project":"king cage","count":1021,"countBy":"average","dictation":false,"end":"2017-05-05T09:35:50","commit":"5b20be68cb19b75fa7d835950fff6e7bafc2238f"},{"location":"home","type":"story","start":"2017-05-05T10:15:23","path":"/Users/msc/Writing/king cage","startCount":126065,"project":"king cage","count":1156,"countBy":"average","dictation":false,"end":"2017-05-05T10:42:35","commit":"bb5c2455956aa125889a0206d0fb77e098ccf3a2"},{"location":"home","type":"story","start":"2017-05-05T11:19:39","path":"/Users/msc/Writing/king cage","startCount":126116,"project":"king cage","count":1078,"countBy":"average","dictation":false,"end":"2017-05-05T11:56:31","commit":"8c62043c58618f0870f5497fb5187de591433449"},{"location":"home","type":"story","start":"2017-05-05T13:05:12","path":"/Users/msc/Writing/king cage","startCount":126202,"project":"king cage","count":892,"countBy":"average","dictation":false,"end":"2017-05-05T13:39:50","commit":"296f0e251c7df8467b2fe0d6d056cecda598b2e9"},{"location":"home","type":"story","start":"2017-05-05T14:57:29","path":"/Users/msc/Writing/king cage","startCount":126165,"project":"king cage","count":959,"countBy":"average","dictation":false,"end":"2017-05-05T15:40:38","commit":"f883d4860ce1e1ddd8a0fbaf0bf0cf05820fac93"},{"location":"home","type":"story","start":"2017-05-06T07:09:09","path":"/Users/msc/Writing/king cage","startCount":126388,"project":"king cage","count":856,"countBy":"average","dictation":false,"end":"2017-05-06T07:46:24","commit":"ba78d0adad257dadd905ff0e650273dc720c93e8"},{"location":"home","type":"story","start":"2017-05-06T07:49:01","path":"/Users/msc/Writing/king cage","startCount":126560,"project":"king cage","count":1401,"countBy":"average","dictation":false,"end":"2017-05-06T08:57:22","commit":"bc26eadf4ba1c91e9f5aefb78f0f074ab0d823ca"},{"location":"home","type":"story","start":"2017-05-06T10:01:09","path":"/Users/msc/Writing/king cage","startCount":126955,"project":"king cage","count":1196,"countBy":"average","dictation":false,"end":"2017-05-06T10:30:33","commit":"9d154c1f0aa9a1f754b746663a0f7d819c1c580d"},{"location":"home","type":"story","start":"2017-05-06T11:14:48","path":"/Users/msc/Writing/king cage","startCount":126969,"project":"king cage","count":913,"countBy":"average","dictation":false,"end":"2017-05-06T11:52:01","commit":"2936092a9f86d7e43b3e72643ffb4449377e55f6"},{"location":"home","type":"story","start":"2017-05-06T16:26:11","path":"/Users/msc/Writing/king cage","startCount":127057,"project":"king cage","count":1019,"countBy":"average","dictation":false,"end":"2017-05-06T17:05:10","commit":"84f9e30c4bde8272ed29b0a93a7c65e336736215"},{"location":"home","type":"story","start":"2017-05-07T07:02:30","path":"/Users/msc/Writing/king cage","startCount":127253,"project":"king cage","count":1474,"countBy":"average","dictation":false,"end":"2017-05-07T07:43:14","commit":"e25923ad8041a784fc3641adca472906b47171fe"},{"location":"home","type":"story","start":"2017-05-07T08:02:53","path":"/Users/msc/Writing/king cage","startCount":127284,"project":"king cage","count":1897,"countBy":"average","dictation":false,"end":"2017-05-07T09:06:26","commit":"b48623e01fe83aa69f9f96e6484f05744851d151"},{"location":"home","type":"story","start":"2017-05-07T10:33:57","path":"/Users/msc/Writing/king cage","startCount":127214,"project":"king cage","count":344,"countBy":"average","dictation":false,"end":"2017-05-07T11:01:16","commit":"b75bdef7fefdb7aaa2a645f42fee9178e1b7bef2"},{"location":"home","type":"story","start":"2017-05-07T11:11:11","path":"/Users/msc/Writing/king cage","startCount":127530,"project":"king cage","count":1067,"countBy":"average","dictation":false,"end":"2017-05-07T12:00:42","commit":"3370122f40064cbc1b948f7b521af762f68acc98"},{"location":"home","type":"story","start":"2017-05-07T14:53:25","path":"/Users/msc/Writing/king cage","startCount":127056,"project":"king cage","count":911,"countBy":"average","dictation":false,"end":"2017-05-07T15:35:08","commit":"2739ea0a3b5cc0d88339056446c6d2683ac4a837"},{"location":"home","type":"story","start":"2017-05-08T06:57:27","path":"/Users/msc/Writing/king cage","startCount":112591,"project":"king cage","count":1334,"countBy":"average","dictation":false,"end":"2017-05-08T07:53:28","commit":"bcb36b9184761739a0c0312e826c493d479cda49"},{"location":"home","type":"story","start":"2017-05-08T07:55:18","path":"/Users/msc/Writing/king cage","startCount":112751,"project":"king cage","count":657,"countBy":"average","dictation":false,"end":"2017-05-08T08:24:25","commit":"95e1d1241b0c808a19629fd7e478119e3a1cfebb"},{"location":"home","type":"story","start":"2017-05-08T08:37:17","path":"/Users/msc/Writing/king cage","startCount":112792,"project":"king cage","count":1433,"countBy":"average","dictation":false,"end":"2017-05-08T09:53:16","commit":"8330d2b7c68644cf5c4ba45114a23a94d7102d2d"},{"location":"home","type":"story","start":"2017-05-08T09:56:14","path":"/Users/msc/Writing/king cage","startCount":113025,"project":"king cage","count":370,"countBy":"average","dictation":false,"end":"2017-05-08T10:13:21","commit":"8a5a3a052918a967dfaeac6e211bcda40c4ba895"},{"location":"home","type":"story","start":"2017-05-08T10:48:40","path":"/Users/msc/Writing/king cage","startCount":113120,"project":"king cage","count":1058,"countBy":"average","dictation":false,"end":"2017-05-08T11:40:59","commit":"156321454b06d540005fef4096f2b3b807de26f1"},{"location":"home","type":"story","start":"2017-05-08T11:55:40","path":"/Users/msc/Writing/king cage","startCount":112982,"project":"king cage","count":394,"countBy":"average","dictation":false,"end":"2017-05-08T12:08:56","commit":"9810ed5e468699ace7b1bf052c7e7d221adaf462"},{"location":"home","type":"story","start":"2017-05-08T13:15:15","path":"/Users/msc/Writing/king cage","startCount":112909,"project":"king cage","count":1445,"countBy":"average","dictation":false,"end":"2017-05-08T14:35:51","commit":"414112b472bce00f0016815cf345320486c91689"},{"location":"home","type":"write","start":"2017-05-10T07:20:01","path":"/Users/msc/Writing/king cage","startCount":113944,"project":"king cage","count":235,"countBy":"average","dictation":false,"end":"2017-05-10T07:53:21","commit":"a81def3f938f97f6ce8bc69a97c8c902bd65b435"},{"location":"home","type":"line","start":"2017-05-10T08:18:38","path":"/Users/msc/Writing/king cage","startCount":114201,"project":"king cage","count":1545,"countBy":"average","dictation":false,"end":"2017-05-10T09:05:49","commit":"0893c7c08a2c09abccd64148f47a5b21659d58fe"},{"location":"home","type":"line","start":"2017-05-10T09:53:09","path":"/Users/msc/Writing/king cage","startCount":114169,"project":"king cage","count":1700,"countBy":"average","dictation":false,"end":"2017-05-10T11:18:53","commit":"a3dea24f5acb05adfcce3ffb455cb6daeedc0464"},{"location":"cafe","type":"write","start":"2017-05-15T08:46:30","path":"/Users/msc/Writing/king cage","startCount":114134,"project":"king cage","count":791,"countBy":"average","dictation":false,"end":"2017-05-15T10:09:26","commit":"a772142e37990e23b7c9f39c2c84711171128ed7"},{"location":"cafe","type":"write","start":"2017-05-15T10:23:58","path":"/Users/msc/Writing/king cage","startCount":114914,"project":"king cage","count":438,"end":"2017-05-15T11:05:00","countBy":"average","dictation":false,"commit":"a5feff1864d3136882680e78978155611358457c"},{"location":"cafe","type":"write","start":"2017-05-16T09:04:20","path":"/Users/msc/Writing/king cage","startCount":115067,"project":"king cage","count":145,"countBy":"average","dictation":false,"end":"2017-05-16T09:22:18","commit":"2b47bdf3f8a5522f2aa518da3d87715c5015c61a"},{"location":"cafe","type":"line","start":"2017-05-17T09:12:27","path":"/Users/msc/Writing/king cage","startCount":115220,"project":"king cage","count":1299,"countBy":"average","dictation":false,"end":"2017-05-17T10:02:33","commit":"27058707111c031afa80818c7bcbe897ca5c51ce"},{"location":"cafe","type":"line","start":"2017-05-18T07:53:27","path":"/Users/msc/Writing/king cage","startCount":115144,"project":"king cage","count":886,"countBy":"average","dictation":false,"end":"2017-05-18T08:19:03","commit":"d2f51cbf90fc2cd5f6e5aff45ead160b3c45c129"},{"location":"cafe","type":"line","start":"2017-05-18T09:01:03","path":"/Users/msc/Writing/king cage","startCount":129058,"project":"king cage","count":678,"countBy":"average","dictation":false,"end":"2017-05-18T09:17:07","commit":"c1f9060a1b4e126706846e5f52da12e35349c693"},{"location":"cafe","type":"line","start":"2017-05-18T10:01:27","path":"/Users/msc/Writing/king cage","startCount":128982,"project":"king cage","count":1302,"countBy":"average","dictation":false,"end":"2017-05-18T10:15:19","commit":"26d85e2c8d5011079c7093e12bd3f5c79779520a"},{"location":"cafe","type":"line","start":"2017-05-18T10:57:08","path":"/Users/msc/Writing/king cage","startCount":128976,"project":"king cage","count":929,"countBy":"average","dictation":false,"end":"2017-05-18T11:15:50","commit":"2817fbfb8f5a775746ff6071f6e40d9e850dda56"},{"location":"park","type":"line","start":"2017-05-18T13:23:54","path":"/Users/msc/Writing/king cage","startCount":128944,"project":"king cage","count":954,"countBy":"average","dictation":false,"end":"2017-05-18T13:42:44","commit":"f699ddc7fccabe625a38a83d33e2cfed8d0c4212"},{"location":"cafe","type":"line","start":"2017-05-19T08:29:32","path":"/Users/msc/Writing/king cage","startCount":128943,"project":"king cage","count":1163,"countBy":"average","dictation":false,"end":"2017-05-19T09:19:33","commit":"90d996b02606143e1e8c7985eda6f4b7d543f94b"},{"location":"cafe","type":"line","start":"2017-05-19T09:49:05","path":"/Users/msc/Writing/king cage","startCount":128852,"project":"king cage","count":1115,"countBy":"average","dictation":false,"end":"2017-05-19T10:37:03","commit":"488962b8bc91c1094ff6b3399982182215479a7f"},{"location":"cafe","type":"line","start":"2017-05-20T09:38:08","path":"/Users/msc/Writing/king cage","startCount":128788,"project":"king cage","count":1241,"countBy":"average","dictation":false,"end":"2017-05-20T10:25:42","commit":"3603c7c598f8ee39288cd42a4c5a1332a2d4c0fe"},{"location":"cafe","type":"write","start":"2017-05-22T09:45:38","path":"/Users/msc/Writing/king cage","startCount":128728,"project":"king cage","count":567,"countBy":"average","dictation":false,"end":"2017-05-22T10:36:35","commit":"cccc71b324331cf27a4cb873509e2b6bdde1bb57"},{"location":"cafe","type":"write","start":"2017-05-22T11:23:58","path":"/Users/msc/Writing/king cage","startCount":129294,"project":"king cage","count":218,"countBy":"average","dictation":false,"end":"2017-05-22T11:34:02","commit":"3d47f0827b97397e178e5e18a64be66f15ec8740"},{"location":"cafe","type":"write","start":"2017-05-22T11:49:24","path":"/Users/msc/Writing/king cage","startCount":129524,"project":"king cage","count":182,"countBy":"average","dictation":false,"end":"2017-05-22T12:05:20","commit":"6ad1a456ef12a65844dfa7ad01d306053efd8131"},{"location":"cafe","type":"line","start":"2017-05-23T10:09:03","path":"/Users/msc/Writing/king cage","startCount":129545,"project":"king cage","count":1516,"countBy":"average","dictation":false,"end":"2017-05-23T11:02:08","commit":"9ef16c443c1cdee268c5b21ea8601cac72719d35"},{"location":"home","type":"line","start":"2017-05-23T13:26:34","path":"/Users/msc/Writing/king cage","startCount":129666,"project":"king cage","count":1258,"countBy":"average","dictation":false,"end":"2017-05-23T14:00:26","commit":"ddfd8b149c0ffe4d5a5ceedfc1f1dc22323c67b7"},{"location":"home","type":"line","start":"2017-05-23T14:58:10","path":"/Users/msc/Writing/king cage","startCount":129657,"project":"king cage","count":1315,"countBy":"average","dictation":false,"end":"2017-05-23T15:17:11","commit":"19ee01f6fb8d852fc0ef080ba440ac21e3f87756"},{"location":"home","type":"line","start":"2017-05-23T19:19:28","path":"/Users/msc/Writing/king cage","startCount":129650,"project":"king cage","count":3046,"countBy":"average","dictation":false,"end":"2017-05-23T20:42:42","commit":"774530813cb0515ae0ffb008b2d0abfab942dbe7"},{"location":"cafe","type":"line","start":"2017-05-24T10:09:28","path":"/Users/msc/Writing/king cage","startCount":129701,"project":"king cage","count":1469,"countBy":"average","dictation":false,"end":"2017-05-24T11:35:35","commit":"0a0ecaa2ebdf7a7409c306420f119f16a0b27f09"},{"location":"cafe","type":"line","start":"2017-05-24T11:49:27","path":"/Users/msc/Writing/king cage","startCount":129904,"project":"king cage","count":1265,"countBy":"average","dictation":false,"end":"2017-05-24T12:28:57","commit":"a3e2ed8e8fd122827e646d7cee744b29e40e50c0"},{"location":"cafe","type":"line","start":"2017-05-24T12:58:47","path":"/Users/msc/Writing/king cage","startCount":129934,"project":"king cage","count":1727,"countBy":"average","dictation":false,"end":"2017-05-24T14:07:16","commit":"60134e2ed13def45e02a9a4f990535449bb5f770"},{"location":"home","type":"line","start":"2017-05-24T14:41:59","path":"/Users/msc/Writing/king cage","startCount":130119,"project":"king cage","count":2593,"countBy":"average","dictation":false,"end":"2017-05-24T15:59:12","commit":"7352ccac8e31cad722c0552b806dc4c1151f8601"},{"location":"home","type":"line","start":"2017-05-25T12:31:09","path":"/Users/msc/Writing/king cage","startCount":130028,"project":"king cage","count":1679,"countBy":"average","dictation":false,"end":"2017-05-25T13:38:12","commit":"d51c86d9bf5dc3f398549bb099b411d9a43c9321"},{"location":"home","type":"line","start":"2017-05-25T14:36:25","path":"/Users/msc/Writing/king cage","startCount":129990,"project":"king cage","count":1105,"countBy":"average","dictation":false,"end":"2017-05-25T15:11:29","commit":"8b164d481427f8dd9b3196cedf936e0e7c2a7a73"},{"location":"home","type":"line","start":"2017-05-25T15:48:45","path":"/Users/msc/Writing/king cage","startCount":130042,"project":"king cage","count":542,"countBy":"average","dictation":false,"end":"2017-05-25T16:12:21","commit":"767d647819959a585afcdab7d150c8b53f5cfed9"},{"location":"home","type":"line","start":"2017-05-26T06:54:59","path":"/Users/msc/Writing/king cage","startCount":130006,"project":"king cage","count":486,"countBy":"average","dictation":false,"end":"2017-05-26T07:16:29","commit":"2d6e33e74c3364c1a944a79d33eca6d6dee97d7e"},{"location":"home","type":"line","start":"2017-05-26T07:21:59","path":"/Users/msc/Writing/king cage","startCount":130063,"project":"king cage","count":895,"countBy":"average","dictation":false,"end":"2017-05-26T08:00:18","commit":"8ca640c890351eb991bb6068a20f98f38421d7a0"},{"location":"home","type":"line","start":"2017-05-26T08:10:32","path":"/Users/msc/Writing/king cage","startCount":129828,"project":"king cage","count":950,"countBy":"average","dictation":false,"end":"2017-05-26T08:40:07","commit":"56a58cf784ab8e757514dc02a35d73d7734b3e5e"},{"location":"home","type":"line","start":"2017-05-26T08:43:09","path":"/Users/msc/Writing/king cage","startCount":129738,"project":"king cage","count":982,"countBy":"average","dictation":false,"end":"2017-05-26T09:22:59","commit":"b224ed12d8a18f1e8ba434701a0018faca6ae356"},{"location":"home","start":"2017-05-26T09:30:00","type":"line","path":"/Users/msc/Writing/king cage","startCount":129898,"project":"king cage","count":745,"countBy":"average","dictation":false,"end":"2017-05-26T09:45:35"},{"location":"home","type":"line","start":"2017-05-26T09:47:36","path":"/Users/msc/Writing/king cage","startCount":129898,"project":"king cage","count":715,"countBy":"average","dictation":false,"end":"2017-05-26T10:07:57","commit":"c7bb7a7f7ffe5c16a21333e60e9b2f816229d548"}]
